sbf_parser/__init__.py
sbf_parser/block_parsers.c
sbf_parser/block_parsers.cpython-312-x86_64-linux-gnu.so
sbf_parser/block_parsers.pxd
sbf_parser/block_parsers.pyx
sbf_parser/block_parsers_generator.py
sbf_parser/block_structure.py
sbf_parser/c_crc.c
sbf_parser/c_crc.h
sbf_parser/encoder.c
sbf_parser/encoder.cpython-312-x86_64-linux-gnu.so
sbf_parser/encoder.pxd
sbf_parser/encoder.pyx
sbf_parser/memory.c
sbf_parser/memory.cpython-312-x86_64-linux-gnu.so
sbf_parser/memory.pxd
sbf_parser/memory.pyx
sbf_parser/parser.c
sbf_parser/parser.cpython-312-x86_64-linux-gnu.so
sbf_parser/parser.pxd
sbf_parser/parser.pyx
sbf_parser/utils.py
sbf_parser-1.0.3.dist-info/METADATA
sbf_parser-1.0.3.dist-info/WHEEL
sbf_parser-1.0.3.dist-info/top_level.txt
sbf_parser-1.0.3.dist-info/RECORD
sbf_parser-1.0.3.dist-info/licenses/LICENSE
