Metadata-Version: 2.4
Name: sbf_parser
Version: 1.0.3
Summary: A Python module (in Cython) to parse SBF stream generated by Septentrio receivers.
Author-email: Jashandeep Sohi <jashandeep.s.sohi@gmail.com>, Marco Job <marco.job@bluewin.ch>, Méven Jeanne-Rose <meven.j.r@gmail.com>, Louis-Max Harter <louis-max.harter@protonmail.com>, Loïc Dubois <loc.21.dubois@gmail.com>
License: MIT
Project-URL: Homepage, https://github.com/septentrio-gnss/SbfParser
Project-URL: Bug Tracker, https://github.com/septentrio-gnss/SbfParser/issues
Classifier: Programming Language :: Python :: 3
Classifier: Programming Language :: Cython
Classifier: Operating System :: OS Independent
Requires-Python: >=3.7
License-File: LICENSE
Dynamic: license-file
